{
  "soc": "Ascend910B4",
  "description": "First-pass 910B4 configuration for kernel_evaluation matmul evaluator. Replace assumed fields with CANN platform config values when available.",
  "sources": {
    "aic_num": "profiling AI_CORE Block Dim observed as 20",
    "aiv_num": "assumed 2x AIC for 910B class devices",
    "hbm_bandwidth_tbps": "user supplied",
    "cache_sizes": "assumed from common AscendC-style 910B/arch35 configuration; update if platform config is available",
    "peak_tflops": "initial no-HF32 working assumptions; update if official 910B4 values are available"
  },
  "aic_num": 20,
  "aiv_num": 40,
  "hbm_bandwidth_tbps": 0.8,
  "l0a_bytes": 65536,
  "l0b_bytes": 65536,
  "l0c_bytes": 262144,
  "l1_bytes": 524288,
  "l2_bytes": 201326592,
  "ub_bytes": 196608,
  "bt_bytes": 4096,
  "kernel_model": {
    "runtime_kb": {
      "enabled": true,
      "matmul_v3_paths": [
        "ops-nn-master-matmul-mat_mul_v3/matmul/mat_mul_v3/op_host/config/ascend910b/Ascend910B4_20_AiCore_MatMulV3_runtime_kb.json"
      ]
    },
    "advanced_tiling": {
      "enabled": false,
      "arch": "non_advanced_ascend910b",
      "applies_to": [
        "MatMulV3",
        "BatchMatMulV3"
      ],
      "notes": "910B4 uses the non-advanced host tiling path in the checked-in ops-nn source; runtime_kb exact hits are used when available."
    }
  },
  "peak_tflops": {
    "FLOAT16": 240.0,
    "DT_BF16": 240.0,
    "BFLOAT16": 240.0,
    "FLOAT": 64.0,
    "FLOAT32": 64.0,
    "INT8": 600.0
  },
  "quant_matmul": {
    "description": "Initial explicit model knobs for QuantBatchMatmulV3. These are effective device-level TOPS and pipeline terms, not per-shape fitted curves.",
    "peak_tops": {
      "INT8": 600.0,
      "INT4": 1200.0,
      "MXFP8": 600.0
    },
    "pipeline_efficiency": {
      "default": 0.60,
      "INT8": 0.522674,
      "INT4": 0.55,
      "MXFP8": 0.60
    },
    "operation_factor": {
      "full_quant": 1.0,
      "full_quant_with_dequant": 1.0,
      "weight_only_quant": 1.0,
      "weight_only_quant_with_dequant": 1.0,
      "fake_quant_or_mixed": 2.0
    },
    "dequant_us_per_output_element": 0.0,
    "scale_replay_factor": 1.0
  },
  "calibration": {
    "launch_overhead_us_by_type": {
      "default": 0.0,
      "BatchMatMul": 2.35824,
      "MatMul": 3.6392,
      "MatMulV2": 3.1942,
      "MatMulV3": 0.0,
      "BatchMatMulV2": 0.0,
      "QuantBatchMatmulV3": 0.0
    },
    "pipeline_efficiency_by_dtype": {
      "default": 1.0,
      "FLOAT16": 0.976532,
      "DT_BF16": 0.922814,
      "BFLOAT16": 0.922814,
      "FLOAT": 0.99724,
      "FLOAT32": 0.99724
    },
    "format_overhead_us": {
      "default": 0.0,
      "ND2NZ": 0.0,
      "FRACTAL_NZ": 0.0,
      "NON_CONTIGUOUS": 0.0
    }
  }
}
